MANIFEST.in
README.rst
setup.py
metayaml/__init__.py
metayaml/metayaml.py
metayaml/test.py
metayaml.egg-info/PKG-INFO
metayaml.egg-info/SOURCES.txt
metayaml.egg-info/dependency_links.txt
metayaml.egg-info/requires.txt
metayaml.egg-info/top_level.txt
metayaml/test_files/cp.yaml
metayaml/test_files/dict_update.yaml
metayaml/test_files/f1.yaml
metayaml/test_files/f2.yaml
metayaml/test_files/f3.yaml
metayaml/test_files/inherit.yaml
metayaml/test_files/inherit_deepcp.yaml
metayaml/test_files/test.yaml
metayaml/test_files/test_list.yaml
metayaml/test_files/test_multi.yaml
metayaml/test_files/test_order.yaml
metayaml/test_files/undef.yaml
metayaml/test_files/undef2.yaml