Metadata-Version: 1.1
Name: metayaml
Version: 0.25
Summary: Enhancements of yaml format to support include and python expression
Home-page: https://bitbucket.org/atagunov/metayaml/
Author: Anton Tagunov
Author-email: UNKNOWN
License: UNKNOWN
Platform: UNKNOWN
Classifier: Programming Language :: Python
Classifier: Programming Language :: Python :: 3
Classifier: Development Status :: 4 - Beta
Classifier: Intended Audience :: Developers
Classifier: Natural Language :: English
Classifier: License :: OSI Approved :: MIT License
Classifier: Environment :: Other Environment
Classifier: Operating System :: OS Independent
Classifier: Topic :: Software Development :: Libraries :: Python Modules
